menschmachine/__init__.py
menschmachine/agents.py
menschmachine/callbacks/__init__.py
menschmachine/callbacks/local.py
menschmachine/event/__init__.py
menschmachine/filetypes/code-file-extensions.txt
menschmachine/filetypes/file_types.py
menschmachine/flashspec.py
menschmachine/gitclient.py
menschmachine/llm/claude.py
menschmachine/llm/gemini.py
menschmachine/llm/l4ngch4in.py
menschmachine/llm/lite.py
menschmachine/llm/oai.py
menschmachine/llm/openrouter.py
menschmachine/llm/proxy.py
menschmachine/llm/types.py
menschmachine/log/__init__.py
menschmachine/log/logging.yaml
menschmachine/main.py
menschmachine/patch/__init__.py
menschmachine/patch/answer.xml
menschmachine/patch/answer_example.xml
menschmachine/patch/xml_patch.py
menschmachine/platform_adapter.py
menschmachine/project/__init__.py
menschmachine/util.py
menschmachine/version.py
menschmachine-0.1.217.dist-info/METADATA
menschmachine-0.1.217.dist-info/WHEEL
menschmachine-0.1.217.dist-info/entry_points.txt
menschmachine-0.1.217.dist-info/RECORD
